tree2repo/__init__.py
tree2repo/cli.py
tree2repo/core.py
tree2repo-0.1.1.dist-info/licenses/LICENSE
tree2repo-0.1.1.dist-info/METADATA
tree2repo-0.1.1.dist-info/WHEEL
tree2repo-0.1.1.dist-info/entry_points.txt
tree2repo-0.1.1.dist-info/top_level.txt
tree2repo-0.1.1.dist-info/RECORD
