Metadata-Version: 2.4
Name: tree2repo
Version: 0.1.1
Summary: Create a repo structure from a pasted tree.
Author-email: Akshan Krithick <akshankrithick305@gmail.com>
License: MIT
Project-URL: Homepage, https://github.com/akshan-main/tree2repo
Project-URL: Source, https://github.com/akshan-main/tree2repo
Project-URL: Issues, https://github.com/akshan-main/tree2repo/issues
Keywords: cli,scaffolding,developer-tools,project-structure
Classifier: Programming Language :: Python :: 3
Classifier: Programming Language :: Python :: 3 :: Only
Classifier: License :: OSI Approved :: MIT License
Classifier: Environment :: Console
Classifier: Intended Audience :: Developers
Requires-Python: >=3.8
License-File: LICENSE
Dynamic: license-file
